README.md
long_desc.txt
setup.py
pma_python/__init__.py
pma_python/control.py
pma_python/core.py
pma_python/core_admin.py
pma_python/pma.py
pma_python/version.py
pma_python/view.py
pma_python.egg-info/PKG-INFO
pma_python.egg-info/SOURCES.txt
pma_python.egg-info/dependency_links.txt
pma_python.egg-info/not-zip-safe
pma_python.egg-info/requires.txt
pma_python.egg-info/top_level.txt