Metadata-Version: 1.2
Name: pma-python
Version: 2.0.0.156
Summary: Universal viewing of digital microscopy, whole slide imaging and digital pathology data
Home-page: http://github.com/pathomation/pma_python
Author: Pathomation
Author-email: info@pathomation.com
License: http://free.pathomation.com/eula/
Keywords: wsi whole slide imaging gigapixel microscopy histology pathology
Platform: UNKNOWN
Classifier: Development Status :: 3 - Alpha
Classifier: Programming Language :: Python :: 3
Requires-Python: >=3
